honeygain/__init__.py
honeygain/client.py
honeygain/exceptions.py
honeygain/http.py
honeygain/schemas.py
Honeygain.py-1.3.0.dist-info/LICENSE
Honeygain.py-1.3.0.dist-info/METADATA
Honeygain.py-1.3.0.dist-info/WHEEL
Honeygain.py-1.3.0.dist-info/top_level.txt
Honeygain.py-1.3.0.dist-info/RECORD
