Metadata-Version: 2.1
Name: Honeygain.py
Version: 1.3.0
Summary: Python wrapper for the Honeygain API.
Home-page: https://github.com/DismissedGuy/honeygain.py
Author: Mike A.
Author-email: dismissed.is.a.guy@gmail.com
License: GPLv3
Classifier: Development Status :: 4 - Beta
Classifier: License :: OSI Approved :: GNU General Public License v3 (GPLv3)
Classifier: Operating System :: OS Independent
License-File: LICENSE
Requires-Dist: requests (<2.28,>=2.27)
Requires-Dist: pydantic (<1.10.0,>=1.9.0)
